TreeAnalysis
