Metadata-Version: 2.1
Name: TreeAnalysis
Version: 0.0.0.4
Summary: Processing one-many json files.
Home-page: https://github.com/Tsangares/address
Author-email: william.wyatt@cgu.edu
License: UNKNOWN
Platform: UNKNOWN
Classifier: Programming Language :: Python :: 3
Classifier: License :: OSI Approved :: MIT License
Classifier: Operating System :: OS Independent
Requires-Python: >=3.6
